haptic/__about__.py
haptic/__init__.py
haptic-0.0.1.dist-info/METADATA
haptic-0.0.1.dist-info/WHEEL
haptic-0.0.1.dist-info/licenses/LICENSE.txt
haptic-0.0.1.dist-info/RECORD
